{"cameraMode":{"drawMode":0,"name":"Shaded","section":"Shading Mode"},"sceneLighting":true,"audioPlay":false,"sceneViewState":{"m_AlwaysRefresh":false,"showFog":true,"showSkybox":true,"showFlares":true,"showImageEffects":true,"showParticleSystems":true,"showVisualEffectGraphs":true,"m_FxEnabled":true},"in2DMode":false,"pivot":{"x":7.744224548339844,"y":2.110820770263672,"z":5.2707648277282719},"rotation":{"x":-0.20427213609218598,"y":-0.36714109778404238,"z":0.08298994600772858,"w":-0.9036729335784912},"size":8.7098388671875,"orthographic":false}